artron
