Metadata-Version: 2.1
Name: artron
Version: 0.0.5
Summary: Artron - multiprocessing with dependency graph and queue management allowing easy tool creation.
Home-page: https://github.com/ahmet2mir/python-artron.git
Author: Ahmet Demir
Author-email: me@ahmet2mir.eu
License: Apache 2.0
Keywords: artron,multiprocessing,parallel
Platform: UNKNOWN
Classifier: Development Status :: 2 - Pre-Alpha
Classifier: Intended Audience :: Developers
Classifier: License :: OSI Approved :: Apache Software License
Classifier: Operating System :: OS Independent
Classifier: Programming Language :: Python
Classifier: Programming Language :: Python :: 2.7
Classifier: Programming Language :: Python :: 3.4
Classifier: Programming Language :: Python :: 3.5
Classifier: Programming Language :: Python :: 3.6
Classifier: Programming Language :: Python :: 3.7
Classifier: Topic :: Software Development :: Build Tools
Requires-Python: >=2.7,!=3.0.*,!=3.1.*,!=3.2.*,!=3.3.*
